{
  "categories": [
    {
      "name": "Programming Languages",
      "items": [
        "Java",
        "C",
        "Python",
        "JavaScript"
      ]
    },
    {
      "name": "Frontend",
      "items": [
        "React",
        "Next.js",
        "Tailwind CSS",
        "Framer Motion",
        "HTML5",
        "CSS3"
      ]
    },
    {
      "name": "Backend",
      "items": [
        "Node.js",
        "Express",
        "Python",
        "Java",
        "REST APIs"
      ]
    },
    {
      "name": "Database",
      "items": [
        "PostgreSQL",
        "MongoDB",
        "MySQL"
      ]
    },
    {
      "name": "AI / Machine Learning",
      "items": [
        "NumPy",
        "Pandas",
        "OpenCV",
        "Computer Vision Basics"
      ]
    },
    {
      "name": "DevOps & Tools",
      "items": [
        "Docker",
        "Git",
        "GitHub",
        "AWS (EC2, S3)",
        "Vercel",
        "Postman",
        "Linux",
        "Figma",
        "Bash Scripting"
      ]
    }
  ]
}
